{
  "date": "2025-01-05",
  "summary": "- package.json: 11 changes\n- LICENSE.md: 6 changes\n- README.md: 6 changes\n- git-contributions-0.0.1.vsix: 2 changes",
  "statistics": {
    "totalFiles": 4,
    "totalChanges": 25,
    "mostEditedFile": "package.json",
    "workDuration": "1h 24m",
    "fileTypes": {
      "json": 11,
      "vsix": 2,
      "md": 12
    },
    "peakActivityHour": "16:00-17:00",
    "totalLinesChanged": 1305
  },
  "projectDetails": {
    "branch": "unknown",
    "commitHash": "unknown",
    "remote": "unknown",
    "name": "unknown"
  }
}